alquimia_client/__init__.py
alquimia_client/main.py
alquimia_client/py.typed
alquimia_client-0.1.1.dist-info/licenses/LICENSE
alquimia_client-0.1.1.dist-info/METADATA
alquimia_client-0.1.1.dist-info/WHEEL
alquimia_client-0.1.1.dist-info/top_level.txt
alquimia_client-0.1.1.dist-info/RECORD
