Metadata-Version: 2.4
Name: alquimia-client
Version: 0.1.1
Summary: Seamslesly connect your apps with Alquimia Runtime API
Project-URL: repository, https://github.com/alquimia-ai/alquimia-python-client.git
Requires-Python: >=3.11
License-File: LICENSE
Requires-Dist: httpx
Requires-Dist: pydantic
Dynamic: license-file
